core/__init__.py
core/api/__init__.py
core/api/classes/__init__.py
core/api/classes/api.py
core/api/classes/api_channel.py
core/api/classes/api_channel_collection.py
core/api/classes/api_channel_event.py
core/api/classes/api_channel_event_collection.py
core/api/classes/api_endpoint.py
core/api/classes/api_endpoint_collection.py
core/api/mixins/__init__.py
core/api/mixins/api_mixin.py
core/client/__init__.py
core/client/classes/__init__.py
core/client/classes/http_client.py
core/client/classes/http_client_session.py
core/client/classes/http_request.py
core/client/classes/http_response.py
core/client/classes/ws_client.py
core/client/classes/ws_client_session.py
core/client/classes/ws_connection.py
core/client/enums/__init__.py
core/client/enums/http_method.py
core/client/exceptions/__init__.py
core/client/functions/__init__.py
core/client/functions/http_delete.py
core/client/functions/http_get.py
core/client/functions/http_post.py
core/client/functions/http_request.py
core/client/types/__init__.py
core/collection/__init__.py
core/collection/classes/__init__.py
core/collection/classes/collection.py
core/collection/classes/dict_collection.py
core/collection/classes/list_collection.py
core/collection/classes/ring_collection.py
core/collection/exceptions/__init__.py
core/collection/functions/__init__.py
core/collection/functions/filter_checkers.py
core/collection/functions/filter_conditions.py
core/datetime/__init__.py
core/datetime/functions/__init__.py
core/datetime/functions/dtnow.py
core/datetime/functions/dtto_utc.py
core/dict/__init__.py
core/dict/classes/__init__.py
core/dict/classes/dict_schema_context.py
core/dict/functions/__init__.py
core/dict/functions/dfrom_schema.py
core/dict/functions/dget.py
core/dict/functions/dset.py
core/dict/types/__init__.py
core/log/__init__.py
core/log/classes/__init__.py
core/log/classes/log.py
core/log/classes/log_collection.py
core/log/classes/logger.py
core/log/exceptions/__init__.py
core/object/__init__.y
python_core_utilities-0.2.6.dist-info/LICENSE
python_core_utilities-0.2.6.dist-info/METADATA
python_core_utilities-0.2.6.dist-info/WHEEL
python_core_utilities-0.2.6.dist-info/RECORD
